pyIMD/__init__.py
pyIMD/imd.py
pyIMD/imd.py.BASE.py
pyIMD/imd.py.LOCAL.py
pyIMD/imd.py.REMOTE.py
pyIMD/main.py
pyIMD/temp.py
pyIMD/test.py
pyIMD/analysis/__init__.py
pyIMD/analysis/calculations.py
pyIMD/analysis/curve_fit.py
pyIMD/configuration/__init__.py
pyIMD/configuration/config.py
pyIMD/configuration/defaults.py
pyIMD/error/__init__.py
pyIMD/error/error_handler.py
pyIMD/examples/example_report.py
pyIMD/examples/example_usage_script.py
pyIMD/examples/example_usage_script_nanonis_longterm.py
pyIMD/io/__init__.py
pyIMD/io/read_from_disk.py
pyIMD/io/write_to_disk.py
pyIMD/plotting/__init__.py
pyIMD/plotting/figures.py
pyIMD/tests/__init__.py
pyIMD/tests/debug.py
pyIMD/tests/test_analysis.py
pyIMD/tests/test_configuration.py
pyIMD/tests/test_imd.py
pyIMD/tests/test_io.py
pyIMD/tests/test_plotting.py
pyIMD/tests/test_sample.py
pyIMD/ui/__init__.py
pyIMD/ui/help.py
pyIMD/ui/main_ui.py
pyIMD/ui/resource_path.py
pyIMD/ui/settings.py
pyIMD/ui/table_view_models.py
pyIMD/ui/tools.py
pyIMD-0.0.8.dist-info/AUTHORS.rst
pyIMD-0.0.8.dist-info/LICENSE.rst
pyIMD-0.0.8.dist-info/METADATA
pyIMD-0.0.8.dist-info/WHEEL
pyIMD-0.0.8.dist-info/top_level.txt
pyIMD-0.0.8.dist-info/RECORD
