Metadata-Version: 2.1
Name: pyIMD
Version: 0.0.8
Summary: Inertial mass determination
Home-page: https://gitlab.com/csb.ethz/pyIMD/tree/master
Author: Andreas P. Cuny <andreas.cuny@bsse.ethz.ch>, Gotthold Fläschner <gotthold.flaeschner@bsse.ethz.ch>
Author-email: andreas.cuny@bsse.ethz.ch
License: GPL3.0
Download-URL: https://gitlab.com/csb.ethz/pyIMD/tree/master
Keywords: Inertial mass determination
Platform: UNKNOWN
Classifier: Development Status :: 5 - Production/Stable
Classifier: Intended Audience :: Science/Research
Classifier: Natural Language :: English
Classifier: Operating System :: POSIX :: Linux
Classifier: Operating System :: MacOS :: MacOS X
Classifier: Operating System :: Microsoft :: Windows :: Windows 7
Classifier: Programming Language :: Python :: 3
Classifier: License :: OSI Approved :: GNU General Public License v3 (GPLv3)
Classifier: Topic :: Scientific/Engineering
Requires-Dist: pandas (>=0.20.0)
Requires-Dist: numpy (>=1.14.5)
Requires-Dist: scipy (<1.3.0)
Requires-Dist: nptdms (>=0.12.0)
Requires-Dist: tqdm (>=4.23.4)
Requires-Dist: plotnine
Requires-Dist: PyQT5
Requires-Dist: lxml
Requires-Dist: xmltodict
Requires-Dist: matplotlib
Requires-Dist: pyyaml
Requires-Dist: pyqtgraph
Requires-Dist: xmlunittest
